s3localkit/__init__.py
s3localkit/utils.py
s3localkit-0.2.0.dist-info/LICENSE
s3localkit-0.2.0.dist-info/METADATA
s3localkit-0.2.0.dist-info/WHEEL
s3localkit-0.2.0.dist-info/top_level.txt
s3localkit-0.2.0.dist-info/RECORD
